ecsclient/__init__.py
ecsclient/authentication.py
ecsclient/baseclient.py
ecsclient/client.py
ecsclient/schemas.py
ecsclient/common/__init__.py
ecsclient/common/error_codes.py
ecsclient/common/exceptions.py
ecsclient/common/token_request.py
ecsclient/common/util.py
ecsclient/common/cas/__init__.py
ecsclient/common/cas/cas.py
ecsclient/common/configuration/__init__.py
ecsclient/common/configuration/certificate.py
ecsclient/common/configuration/configuration_properties.py
ecsclient/common/configuration/feature.py
ecsclient/common/configuration/licensing.py
ecsclient/common/file_system_access/__init__.py
ecsclient/common/file_system_access/nfs.py
ecsclient/common/geo_replication/__init__.py
ecsclient/common/geo_replication/replication_group.py
ecsclient/common/geo_replication/temporary_failed_zone.py
ecsclient/common/metering/__init__.py
ecsclient/common/metering/billing.py
ecsclient/common/monitoring/__init__.py
ecsclient/common/monitoring/alerts.py
ecsclient/common/monitoring/capacity.py
ecsclient/common/monitoring/dashboard.py
ecsclient/common/monitoring/events.py
ecsclient/common/multitenancy/__init__.py
ecsclient/common/multitenancy/namespace.py
ecsclient/common/multitenancy/tenant.py
ecsclient/common/other/__init__.py
ecsclient/common/other/user_info.py
ecsclient/common/provisioning/__init__.py
ecsclient/common/provisioning/base_url.py
ecsclient/common/provisioning/bucket.py
ecsclient/common/provisioning/data_store.py
ecsclient/common/provisioning/node.py
ecsclient/common/provisioning/storage_pool.py
ecsclient/common/provisioning/vdc_keystore.py
ecsclient/common/provisioning/virtual_data_center.py
ecsclient/common/support/__init__.py
ecsclient/common/support/call_home.py
ecsclient/common/user_management/__init__.py
ecsclient/common/user_management/authentication_provider.py
ecsclient/common/user_management/management_user.py
ecsclient/common/user_management/object_user.py
ecsclient/common/user_management/password_group.py
python_ecsclient_test-1.1.11b1.dist-info/LICENSE
python_ecsclient_test-1.1.11b1.dist-info/METADATA
python_ecsclient_test-1.1.11b1.dist-info/WHEEL
python_ecsclient_test-1.1.11b1.dist-info/top_level.txt
python_ecsclient_test-1.1.11b1.dist-info/RECORD
