Metadata-Version: 2.1
Name: python-ecsclient-test
Version: 1.1.11b1
Summary: A library for interacting with the ECS Management API
Home-page: https://github.com/EMCECS/python-ecsclient
Author: ECS
Author-email: ecs@dell.com
License: UNKNOWN
Keywords: ecsclient
Platform: UNKNOWN
Classifier: Development Status :: 5 - Production/Stable
Classifier: Intended Audience :: Developers
Classifier: License :: OSI Approved :: Apache Software License
Classifier: Operating System :: OS Independent
Classifier: Programming Language :: Python
Classifier: Programming Language :: Python :: 2
Classifier: Programming Language :: Python :: 2.7
Classifier: Programming Language :: Python :: 3
Classifier: Programming Language :: Python :: 3.4
Classifier: Programming Language :: Python :: 3.5
Classifier: Programming Language :: Python :: 3.6
Classifier: Topic :: Software Development :: Libraries :: Python Modules
License-File: LICENSE
Requires-Dist: requests (<3.0,>=2.18.4)
Requires-Dist: six (<2.0,>=1.11.0)
Requires-Dist: jsonschema (<3.0,>=2.6.0)
